no_seu_tempo/__init__.py
no_seu_tempo/no_seu_tempo.py
no_seu_tempo-1.20250810.dist-info/LICENSE
no_seu_tempo-1.20250810.dist-info/METADATA
no_seu_tempo-1.20250810.dist-info/WHEEL
no_seu_tempo-1.20250810.dist-info/top_level.txt
no_seu_tempo-1.20250810.dist-info/RECORD
