Metadata-Version: 2.1
Name: no_seu_tempo
Version: 1.20250810
Summary: Escreva datas como você fala!
Home-page: https://github.com/julio-cascalles/temp/no_seu_tempo
Author: Júlio Cascalles
Author-email: Julio Cascalles <julio.cascalles@outlook.com>
Project-URL: Homepage, https://github.com/julio-cascalles/temp/no_seu_tempo
Classifier: Programming Language :: Python :: 3
Classifier: License :: OSI Approved :: MIT License
Classifier: Operating System :: OS Independent
Requires-Python: >=3.8
License-File: LICENSE
